{
  "id": "tmdb-83533",
  "slug": "avatar-fire-and-ash-2025",
  "title": "Avatar: Fire and Ash",
  "year": 2025,
  "decade": "2020s",
  "industries": [
    "hollywood"
  ],
  "countries": [
    "united-states"
  ],
  "languages": [
    "english"
  ],
  "genres": [
    "science-fiction",
    "adventure",
    "fantasy"
  ],
  "posterUrl": "https://image.tmdb.org/t/p/w500/bRBeSHfGHwkEpImlhxPmOcUsaeg.jpg",
  "backdropUrl": "https://image.tmdb.org/t/p/w1280/u8DU5fkLoM5tTRukzPC31oGPxaQ.jpg",
  "posterAlt": "Avatar: Fire and Ash (2025) movie poster",
  "tmdbOverview": "In the wake of the devastating war against the RDA and the loss of their eldest son, Jake Sully and Neytiri face a new threat on Pandora: the Ash People, a violent and power-hungry Na'vi tribe led by the ruthless Varang. Jake's family must fight for their survival and the future of Pandora in a conflict that pushes them to their emotional and physical limits.",
  "tmdbRating": 7.6,
  "tmdbVotes": 3551,
  "imdbRating": 7.3,
  "imdbId": "tt1757678",
  "popularity": 123.1454,
  "certification": "PG-13",
  "certificationCountry": "US",
  "contentDescriptors": [],
  "synopsis": "Released in 2025, Avatar: Fire and Ash is a science fiction, adventure and fantasy film from United States. It holds a solid 7.3 rating on IMDb. It appears on several of our curated Top 10 lists. It carries a PG-13 certification (US rating system) — see the film's page for parental details.",
  "synopsisAuto": true
}
