{
  "id": "tmdb-706712",
  "slug": "beauty-water-2020",
  "title": "Beauty Water",
  "originalTitle": "기기괴괴 성형수",
  "year": 2020,
  "decade": "2020s",
  "industries": [],
  "countries": [
    "south-korea"
  ],
  "languages": [
    "korean"
  ],
  "genres": [
    "animation",
    "drama",
    "horror",
    "k-drama"
  ],
  "studios": [],
  "themes": [],
  "posterUrl": "https://image.tmdb.org/t/p/w500/pFotlGivCvAWi3SvPycacqju6dN.jpg",
  "backdropUrl": "https://image.tmdb.org/t/p/w1280/2jeH5eMbA7TUHYuIzwKZZgJoQ6V.jpg",
  "posterAlt": "Beauty Water (2020) movie poster",
  "tmdbOverview": "Beauty Water looks like a common skin cosmetic. But unlike other cosmetics, people can sculpt their skin with it like molding clay and change their appearance. An ordinary girl, Yaeji, comes across the 'Beauty Water' by chance, and her endless desire to be the most beautiful woman brings her unimaginable disaster.",
  "tmdbRating": 5.7,
  "tmdbVotes": 54,
  "imdbRating": 6.1,
  "imdbId": "tt12354886",
  "popularity": 0.8765,
  "certification": "16",
  "certificationCountry": "DE",
  "contentDescriptors": [],
  "synopsis": "Released in 2020, Beauty Water is a animation, drama and horror film from South Korea. It carries a 6.1 rating on IMDb. It appears on several of our curated Top 10 lists. It carries a 16 certification (DE rating system) — see the film's page for parental details.",
  "synopsisAuto": true
}
