{
  "id": "tmdb-1224993",
  "slug": "dark-nuns-2025",
  "title": "Dark Nuns",
  "originalTitle": "검은 수녀들",
  "year": 2025,
  "decade": "2020s",
  "industries": [],
  "countries": [
    "south-korea"
  ],
  "languages": [
    "korean"
  ],
  "genres": [
    "horror",
    "mystery",
    "thriller",
    "drama",
    "k-drama"
  ],
  "studios": [],
  "themes": [],
  "posterUrl": "https://image.tmdb.org/t/p/w500/2Abt2GgscAGtGAXTrhH44qPhugI.jpg",
  "backdropUrl": "https://image.tmdb.org/t/p/w1280/bQdYYutvomoxfLQK8gTV8Z3qsmv.jpg",
  "posterAlt": "Dark Nuns (2025) movie poster",
  "tmdbOverview": "Desperation drives two nuns to perform an exorcism no nun should attempt. With a possessed child at the mercy of evil and the opposition of the Catholic Church, they take on the dangerous forbidden rituals themselves, putting their immortal souls in grave danger. They must confront the terrifying cost of their sacrilegious actions, but one goal remains: the boy must be saved at all costs.",
  "tmdbRating": 6.2,
  "tmdbVotes": 89,
  "imdbId": "tt32491690",
  "popularity": 3.6458,
  "certification": "+13",
  "certificationCountry": "AR",
  "contentDescriptors": [],
  "synopsis": "Dark Nuns is a 2025 horror, mystery and thriller film from South Korea. It carries a 6.2 rating on TMDb. A standout of 2020s cinema, it earns its spot on our lists. It carries a +13 certification (AR rating system) — see the film's page for parental details.",
  "synopsisAuto": true
}
