{
  "id": "tmdb-508965",
  "slug": "klaus-2019",
  "title": "Klaus",
  "year": 2019,
  "decade": "2010s",
  "industries": [],
  "countries": [
    "spain"
  ],
  "languages": [
    "english"
  ],
  "genres": [
    "animation",
    "family",
    "comedy"
  ],
  "studios": [],
  "themes": [],
  "posterUrl": "https://image.tmdb.org/t/p/w500/q125RHUDgR4gjwh1QkfYuJLYkL.jpg",
  "backdropUrl": "https://image.tmdb.org/t/p/w1280/cYQvXNPZLow73lhspVQ7CYlT3Mi.jpg",
  "posterAlt": "Klaus (2019) movie poster",
  "tmdbOverview": "A selfish postman and a reclusive toymaker form an unlikely friendship, delivering joy to a cold, dark town that desperately needs it.",
  "tmdbRating": 8.2,
  "tmdbVotes": 4693,
  "imdbRating": 8.2,
  "imdbId": "tt4729430",
  "popularity": 4.4478,
  "certification": "PG",
  "certificationCountry": "US",
  "contentDescriptors": [],
  "synopsis": "Klaus is a 2019 animation, family and comedy film from Spain. It's highly rated, holding a strong 8.2 on IMDb. A standout of 2010s cinema, it earns its spot on our lists. It carries a PG certification (US rating system) — see the film's page for parental details.",
  "synopsisAuto": true
}
