{
  "id": "tmdb-603673",
  "slug": "laxmii-2020",
  "title": "Laxmii",
  "originalTitle": "लक्ष्मी",
  "year": 2020,
  "decade": "2020s",
  "industries": [
    "bollywood"
  ],
  "countries": [
    "india"
  ],
  "languages": [
    "hindi"
  ],
  "genres": [
    "horror",
    "comedy"
  ],
  "studios": [],
  "themes": [],
  "posterUrl": "https://image.tmdb.org/t/p/w500/6COHwokEERAjjvlmNF44Xg9BK1y.jpg",
  "backdropUrl": "https://image.tmdb.org/t/p/w1280/hJHfqLvYPz9nMPEZamjifHiXZbr.jpg",
  "posterAlt": "Laxmii (2020) movie poster",
  "tmdbOverview": "Aasif's belief in logic and science shatters when he gets possessed by a transgender's ghost.",
  "tmdbRating": 4.414,
  "tmdbVotes": 58,
  "imdbRating": 2.5,
  "imdbId": "tt10350922",
  "popularity": 5.3347,
  "certification": "MA15+",
  "certificationCountry": "AU",
  "contentDescriptors": [],
  "synopsis": "Released in 2020, Laxmii is a horror and comedy film from India. It has a 2.5 rating on IMDb. It's one of the titles we feature across our 2020s and genre rankings. It carries a MA15+ certification (AU rating system) — see the film's page for parental details.",
  "synopsisAuto": true
}
