{
  "id": "tmdb-1007757",
  "slug": "swapped-2026",
  "title": "Swapped",
  "year": 2026,
  "decade": "2020s",
  "industries": [
    "hollywood"
  ],
  "countries": [
    "united-states",
    "spain"
  ],
  "languages": [
    "english"
  ],
  "genres": [
    "adventure",
    "animation",
    "family",
    "fantasy"
  ],
  "studios": [],
  "themes": [],
  "posterUrl": "https://image.tmdb.org/t/p/w500/tHhxWxge06goXU6ZQH1hj7vK8Hd.jpg",
  "backdropUrl": "https://image.tmdb.org/t/p/w1280/zMwhWailP1WY7sb6AoE6b8ugoy.jpg",
  "posterAlt": "Swapped (2026) movie poster",
  "tmdbOverview": "A small woodland creature and a majestic bird, two natural sworn enemies of the Valley, magically trade places and set off on an adventure of a lifetime to switch back. Their journey soon uncovers a greater threat—one that could endanger not only their species, but the entire valley they call home.",
  "tmdbRating": 8.961,
  "tmdbVotes": 1794,
  "imdbRating": 7.3,
  "imdbId": "tt29552248",
  "popularity": 144.0851,
  "certification": "PG",
  "certificationCountry": "US",
  "contentDescriptors": [],
  "synopsis": "Swapped (2026) is a adventure, animation and family film from United States and Spain. It holds a solid 7.3 rating on IMDb. A standout of 2020s cinema, it earns its spot on our lists. It carries a PG certification (US rating system) — see the film's page for parental details.",
  "synopsisAuto": true
}
