{
  "id": "tmdb-560527",
  "slug": "the-dude-in-me-2019",
  "title": "The Dude in Me",
  "originalTitle": "내안의 그놈",
  "year": 2019,
  "decade": "2010s",
  "industries": [],
  "countries": [
    "south-korea"
  ],
  "languages": [
    "korean"
  ],
  "genres": [
    "fantasy",
    "comedy",
    "action",
    "k-drama"
  ],
  "posterUrl": "https://image.tmdb.org/t/p/w500/3H97tUK5UmgOpjCh6Q7XZ4HW1cG.jpg",
  "backdropUrl": "https://image.tmdb.org/t/p/w1280/f5xCw22fOR6DgDRCpDFGkPbKbmY.jpg",
  "posterAlt": "The Dude in Me (2019) movie poster",
  "tmdbOverview": "Dong-hyun is a high school student. One day, he falls from the rooftop and bumps into Pan-soo who is a passerby. Pan-soo is a member of a criminal organization. When the two men wake up in the hospital, they discover that they have switched bodies.",
  "tmdbRating": 7.788,
  "tmdbVotes": 151,
  "imdbRating": 6.9,
  "imdbId": "tt9759978",
  "popularity": 4.8925,
  "certification": "IIB",
  "certificationCountry": "HK",
  "contentDescriptors": [],
  "synopsis": "Released in 2019, The Dude in Me is a fantasy, comedy and action film from South Korea. It carries a 6.9 rating on IMDb. It's one of the titles we feature across our 2010s and genre rankings. It carries a IIB certification (HK rating system) — see the film's page for parental details.",
  "synopsisAuto": true
}
